odoo/addons/product_analytic/README.rst
odoo/addons/product_analytic/__init__.py
odoo/addons/product_analytic/__manifest__.py
odoo/addons/product_analytic/demo/product_demo.xml
odoo/addons/product_analytic/i18n/ar.po
odoo/addons/product_analytic/i18n/bs.po
odoo/addons/product_analytic/i18n/ca.po
odoo/addons/product_analytic/i18n/cs.po
odoo/addons/product_analytic/i18n/cs_CZ.po
odoo/addons/product_analytic/i18n/de.po
odoo/addons/product_analytic/i18n/en_GB.po
odoo/addons/product_analytic/i18n/es.po
odoo/addons/product_analytic/i18n/es_CO.po
odoo/addons/product_analytic/i18n/es_CR.po
odoo/addons/product_analytic/i18n/es_EC.po
odoo/addons/product_analytic/i18n/es_MX.po
odoo/addons/product_analytic/i18n/et.po
odoo/addons/product_analytic/i18n/fi.po
odoo/addons/product_analytic/i18n/fr.po
odoo/addons/product_analytic/i18n/fr_CH.po
odoo/addons/product_analytic/i18n/hr.po
odoo/addons/product_analytic/i18n/hr_HR.po
odoo/addons/product_analytic/i18n/hu.po
odoo/addons/product_analytic/i18n/it.po
odoo/addons/product_analytic/i18n/ja.po
odoo/addons/product_analytic/i18n/lt.po
odoo/addons/product_analytic/i18n/mk.po
odoo/addons/product_analytic/i18n/mn.po
odoo/addons/product_analytic/i18n/nb.po
odoo/addons/product_analytic/i18n/nl.po
odoo/addons/product_analytic/i18n/nl_BE.po
odoo/addons/product_analytic/i18n/nl_NL.po
odoo/addons/product_analytic/i18n/product_analytic.pot
odoo/addons/product_analytic/i18n/pt.po
odoo/addons/product_analytic/i18n/pt_BR.po
odoo/addons/product_analytic/i18n/pt_PT.po
odoo/addons/product_analytic/i18n/ro.po
odoo/addons/product_analytic/i18n/ru.po
odoo/addons/product_analytic/i18n/sl.po
odoo/addons/product_analytic/i18n/sv.po
odoo/addons/product_analytic/i18n/tr.po
odoo/addons/product_analytic/i18n/tr_TR.po
odoo/addons/product_analytic/i18n/zh_CN.po
odoo/addons/product_analytic/i18n/zh_TW.po
odoo/addons/product_analytic/models/__init__.py
odoo/addons/product_analytic/models/account_analytic_distribution_model.py
odoo_addon_product_analytic-17.0.1.0.0.2.dist-info/METADATA
odoo_addon_product_analytic-17.0.1.0.0.2.dist-info/WHEEL
odoo_addon_product_analytic-17.0.1.0.0.2.dist-info/top_level.txt
odoo_addon_product_analytic-17.0.1.0.0.2.dist-info/RECORD
